{
  "entries": [
    {
      "question": {
        "name": "faroese:0",
        "type": 5,
        "source": "self-made",
        "collector": "333",
        "language": "Faroese",
        "translations": {
          "Faroese": {
            "language": "Faroese",
            "text": "Hví halda vit Ólavssøku?"
          },
          "English": {
            "language": "English",
            "text": "Why do we celebrate St. Olaf's Day or Wake (29 July)?"
          }
        }
      },
      "answers": []
    },
    {
      "question": {
        "name": "faroese:1",
        "type": 5,
        "source": "self-made",
        "collector": "333",
        "language": "Faroese",
        "translations": {
          "Faroese": {
            "language": "Faroese",
            "text": "Hví siga vit \"Ull er Føroya Gull\"?"
          },
          "English": {
            "language": "English",
            "text": "From whence does the saying \"Wool is the Faroese Gold\" stem from?"
          }
        }
      },
      "answers": []
    },
    {
      "question": {
        "name": "faroese:2",
        "type": 5,
        "source": "self-made",
        "collector": "333",
        "language": "Faroese",
        "translations": {
          "Faroese": {
            "language": "Faroese",
            "text": "Hví halda vit Ovastevnu?"
          },
          "English": {
            "language": "English",
            "text": "Why do we celebrate Ovastevna?"
          }
        }
      },
      "answers": []
    },
    {
      "question": {
        "name": "faroese:3",
        "type": 5,
        "source": "self-made",
        "collector": "333",
        "language": "Faroese",
        "translations": {
          "Faroese": {
            "language": "Faroese",
            "text": "Hví eitur tað Føroyar?"
          },
          "English": {
            "language": "English",
            "text": "Why is it called the Faroe Islands?"
          }
        }
      },
      "answers": []
    },
    {
      "question": {
        "name": "faroese:4",
        "type": 5,
        "source": "self-made",
        "collector": "333",
        "language": "Faroese",
        "translations": {
          "Faroese": {
            "language": "Faroese",
            "text": "Hví læra vit danskt í fólkaskúlanum?"
          },
          "English": {
            "language": "English",
            "text": "Why is Danish taught in primary school?"
          }
        }
      },
      "answers": []
    },
    {
      "question": {
        "name": "faroese:5",
        "type": 5,
        "source": "self-made",
        "collector": "333",
        "language": "Faroese",
        "translations": {
          "Faroese": {
            "language": "Faroese",
            "text": "Hví eitur okkara høvuðsstaður Tórshavn?"
          },
          "English": {
            "language": "English",
            "text": "From where derives our capitals name 'Tórshavn'?"
          }
        }
      },
      "answers": []
    },
    {
      "question": {
        "name": "faroese:6",
        "type": 5,
        "source": "self-made",
        "collector": "333",
        "language": "Faroese",
        "translations": {
          "Faroese": {
            "language": "Faroese",
            "text": "Hvat er er Nólsoyar Páll kendur fyri?"
          },
          "English": {
            "language": "English",
            "text": "What is Nólsoyar Páll famous for?"
          }
        }
      },
      "answers": []
    },
    {
      "question": {
        "name": "faroese:7",
        "type": 5,
        "source": "self-made",
        "collector": "333",
        "language": "Faroese",
        "translations": {
          "Faroese": {
            "language": "Faroese",
            "text": "Hvussu doyði Sigmundur Brestirsson?"
          },
          "English": {
            "language": "English",
            "text": "How did Sigmundur Bestirsson die?"
          }
        }
      },
      "answers": []
    },
    {
      "question": {
        "name": "faroese:8",
        "type": 5,
        "source": "self-made",
        "collector": "333",
        "language": "Faroese",
        "translations": {
          "Faroese": {
            "language": "Faroese",
            "text": "Hví leyp Tróndur í Gøtu á Sigmund Brestirsson?"
          },
          "English": {
            "language": "English",
            "text": "Why did Tróndur í Gøtu attack Sigmundur Brestirsson?"
          }
        }
      },
      "answers": []
    },
    {
      "question": {
        "name": "faroese:9",
        "type": 5,
        "source": "self-made",
        "collector": "333",
        "language": "Faroese",
        "translations": {
          "Faroese": {
            "language": "Faroese",
            "text": "Hví er sjógvurin í Føroyum lutfalsliga heitur?"
          },
          "English": {
            "language": "English",
            "text": "Why is the sea around the Faroe Islands relatively warm?"
          }
        }
      },
      "answers": []
    },
    {
      "question": {
        "name": "faroese:10",
        "type": 5,
        "source": "self-made",
        "collector": "333",
        "language": "Faroese",
        "translations": {
          "Faroese": {
            "language": "Faroese",
            "text": "Hvørji fíggjarlig viðurskifti fingu nógvar føroyingar at flyta av landinum fyrst í 90'unum?"
          },
          "English": {
            "language": "English",
            "text": "Which financial circumstances forced a lot of faroese people to move abroad in the early nineties?"
          }
        }
      },
      "answers": []
    },
    {
      "question": {
        "name": "faroese:11",
        "type": 5,
        "source": "self-made",
        "collector": "333",
        "language": "Faroese",
        "translations": {
          "Faroese": {
            "language": "Faroese",
            "text": "Hví eru vørur framleiddar í ES tollfríar í Føroyum?"
          },
          "English": {
            "language": "English",
            "text": "Why are goods, produced in the EU, exempt from customs?"
          }
        }
      },
      "answers": []
    },
    {
      "question": {
        "name": "faroese:12",
        "type": 5,
        "source": "self-made",
        "collector": "333",
        "language": "Faroese",
        "translations": {
          "Faroese": {
            "language": "Faroese",
            "text": "Hví sita tveir føroyskir politikarar í fólkatinginum?"
          },
          "English": {
            "language": "English",
            "text": "Why are two faroese politicians seated in the danish 'Folketing'?"
          }
        }
      },
      "answers": []
    },
    {
      "question": {
        "name": "faroese:13",
        "type": 5,
        "source": "self-made",
        "collector": "333",
        "language": "Faroese",
        "translations": {
          "Faroese": {
            "language": "Faroese",
            "text": "Hvat tilknýti hevur James Bond til Føroyar?"
          },
          "English": {
            "language": "English",
            "text": "What relation does James Bond have to the Faroe Islands?"
          }
        }
      },
      "answers": []
    },
    {
      "question": {
        "name": "faroese:14",
        "type": 5,
        "source": "self-made",
        "collector": "333",
        "language": "Faroese",
        "translations": {
          "Faroese": {
            "language": "Faroese",
            "text": "Hvat er V.U. Hammershaimb kendur fyri?"
          },
          "English": {
            "language": "English",
            "text": "What is V.U.Hammershaimb famous for?"
          }
        }
      },
      "answers": []
    },
    {
      "question": {
        "name": "faroese:15",
        "type": 5,
        "source": "self-made",
        "collector": "333",
        "language": "Faroese",
        "translations": {
          "Faroese": {
            "language": "Faroese",
            "text": "Hvat er søgan aftanfyri rinkusteinarnir í Oyndarfirði?"
          },
          "English": {
            "language": "English",
            "text": "What is the story behind the 'Rocking stones' in Oyndarfjørður?"
          }
        }
      },
      "answers": []
    },
    {
      "question": {
        "name": "faroese:16",
        "type": 5,
        "source": "self-made",
        "collector": "333",
        "language": "Faroese",
        "translations": {
          "Faroese": {
            "language": "Faroese",
            "text": "Hví halda vit Flaggdagin?"
          },
          "English": {
            "language": "English",
            "text": "Why do we celebrate 'Flaggdagin'?"
          }
        }
      },
      "answers": []
    },
    {
      "question": {
        "name": "faroese:17",
        "type": 5,
        "source": "self-made",
        "collector": "333",
        "language": "Faroese",
        "translations": {
          "Faroese": {
            "language": "Faroese",
            "text": "Hví fáa Føroyar neiligt uppmerksemi orsaka av djóravælferð?"
          },
          "English": {
            "language": "English",
            "text": "Why do we receive negative publicity regarding animal welfare?"
          }
        }
      },
      "answers": []
    },
    {
      "question": {
        "name": "faroese:18",
        "type": 5,
        "source": "self-made",
        "collector": "333",
        "language": "Faroese",
        "translations": {
          "Faroese": {
            "language": "Faroese",
            "text": "Hvør er upprunin til føroyskan dans?"
          },
          "English": {
            "language": "English",
            "text": "Wherefrom does the Faroese Dance originate?"
          }
        }
      },
      "answers": []
    },
    {
      "question": {
        "name": "faroese:19",
        "type": 5,
        "source": "self-made",
        "collector": "333",
        "language": "Faroese",
        "translations": {
          "Faroese": {
            "language": "Faroese",
            "text": "Hvat er Heini havreki kendur fyri?"
          },
          "English": {
            "language": "English",
            "text": "Why is Heini Havreki famous?"
          }
        }
      },
      "answers": []
    },
    {
      "question": {
        "name": "faroese:20",
        "type": 5,
        "source": "self-made",
        "collector": "333",
        "language": "Faroese",
        "translations": {
          "Faroese": {
            "language": "Faroese",
            "text": "Hvat er sermekt við Tinganesi?"
          },
          "English": {
            "language": "English",
            "text": "What is special about Tinganes?"
          }
        }
      },
      "answers": []
    },
    {
      "question": {
        "name": "faroese:21",
        "type": 5,
        "source": "self-made",
        "collector": "333",
        "language": "Faroese",
        "translations": {
          "Faroese": {
            "language": "Faroese",
            "text": "Hví likist tað føroyska málið meira norskum enn donskum?"
          },
          "English": {
            "language": "English",
            "text": "Why does the Faroese language resemble Norwegian more than danish?"
          }
        }
      },
      "answers": []
    },
    {
      "question": {
        "name": "faroese:22",
        "type": 5,
        "source": "self-made",
        "collector": "333",
        "language": "Faroese",
        "translations": {
          "Faroese": {
            "language": "Faroese",
            "text": "Hví loystu Føroyar ikki frá Danmark í 1946, hóast meirluti ynskti loysing?"
          },
          "English": {
            "language": "English",
            "text": "Why didn't we sever with Denmark in 1946, despite majority votes in favor of severance?"
          }
        }
      },
      "answers": []
    },
    {
      "question": {
        "name": "faroese:23",
        "type": 5,
        "source": "self-made",
        "collector": "333",
        "language": "Faroese",
        "translations": {
          "Faroese": {
            "language": "Faroese",
            "text": "Hvat snúði klaksvíksstríðið seg um?"
          },
          "English": {
            "language": "English",
            "text": "What was the 'klaksvíksstríðið' (feud of Klaksvík) all about?"
          }
        }
      },
      "answers": []
    },
    {
      "question": {
        "name": "faroese:24",
        "type": 5,
        "source": "self-made",
        "collector": "333",
        "language": "Faroese",
        "translations": {
          "Faroese": {
            "language": "Faroese",
            "text": "Hvat snýr ósemjan um 'gongd í haga' seg um?"
          },
          "English": {
            "language": "English",
            "text": "What are the arguing points in the feud regarding 'mountain hiking'?"
          }
        }
      },
      "answers": []
    },
    {
      "question": {
        "name": "faroese:25",
        "type": 5,
        "source": "self-made",
        "collector": "572",
        "language": "Faroese",
        "translations": {
          "Faroese": {
            "language": "Faroese",
            "text": "Hví hava útróður og fiskivinna týdning í samfelagnum í dag?"
          },
          "English": {
            "language": "English",
            "text": "Why are boat fishing and the fishing industry important in today's society?"
          }
        }
      },
      "answers": []
    },
    {
      "question": {
        "name": "faroese:26",
        "type": 5,
        "source": "self-made",
        "collector": "572",
        "language": "Faroese",
        "translations": {
          "Faroese": {
            "language": "Faroese",
            "text": "Hvussu hevur seyðahald ávirkað Føroyar búskaparliga og umhvørvisliga?"
          },
          "English": {
            "language": "English",
            "text": "How has sheep farming affected the Faroe Islands economically and environmentally?"
          }
        }
      },
      "answers": []
    },
    {
      "question": {
        "name": "faroese:27",
        "type": 5,
        "source": "self-made",
        "collector": "572",
        "language": "Faroese",
        "translations": {
          "Faroese": {
            "language": "Faroese",
            "text": "Hvussu hevur veðurlagið merkt byggisiðvenjur?"
          },
          "English": {
            "language": "English",
            "text": "How has the climate influenced building traditions?"
          }
        }
      },
      "answers": []
    },
    {
      "question": {
        "name": "faroese:28",
        "type": 5,
        "source": "self-made",
        "collector": "572",
        "language": "Faroese",
        "translations": {
          "Faroese": {
            "language": "Faroese",
            "text": "Hvør er mentanarligi týdningurin av kvæðunum?"
          },
          "English": {
            "language": "English",
            "text": "What is the cultural significance of the ballads?"
          }
        }
      },
      "answers": []
    },
    {
      "question": {
        "name": "faroese:29",
        "type": 5,
        "source": "self-made",
        "collector": "572",
        "language": "Faroese",
        "translations": {
          "Faroese": {
            "language": "Faroese",
            "text": "Hvørji serlig eyðkenni hevur føroysk matmentan?"
          },
          "English": {
            "language": "English",
            "text": "What specific characteristics does Faroese food culture have?"
          }
        }
      },
      "answers": []
    }
  ]
}